{
  "swagger": "2.0",
  "info": {},
  "paths": {
    "/categories/": {
      "get": {
        "description": "Get all categories",
        "tags": [
          "category"
        ],
        "operationId": "getCategory",
        "responses": {
          "200": {
            "$ref": "#/responses/GetAllCategoriesResponse"
          },
          "default": {
            "$ref": "#/responses/GenericResponse"
          }
        }
      }
    },
    "/categories/:id": {
      "get": {
        "description": "Get category by id",
        "tags": [
          "category"
        ],
        "operationId": "getCategory",
        "responses": {
          "200": {
            "$ref": "#/responses/GetOneCategoriesResponse"
          },
          "default": {
            "$ref": "#/responses/GenericResponse"
          }
        }
      }
    },
    "/regions/": {
      "get": {
        "description": "Get all regions",
        "tags": [
          "region"
        ],
        "operationId": "getRegion",
        "responses": {
          "200": {
            "$ref": "#/responses/GetAllRegionsResponse"
          },
          "default": {
            "$ref": "#/responses/GenericResponse"
          }
        }
      }
    },
    "/regions/:id": {
      "get": {
        "description": "Get region by id",
        "tags": [
          "region"
        ],
        "operationId": "getCategory",
        "responses": {
          "200": {
            "$ref": "#/responses/GetOneRegionsResponse"
          },
          "default": {
            "$ref": "#/responses/GenericResponse"
          }
        }
      }
    },
    "/users/:id": {
      "get": {
        "description": "Get one user",
        "tags": [
          "user"
        ],
        "operationId": "getUser",
        "responses": {
          "200": {
            "$ref": "#/responses/GetOneUserResponse"
          },
          "default": {
            "$ref": "#/responses/GenericResponse"
          }
        }
      }
    },
    "/users/signup": {
      "post": {
        "description": "Sign Up",
        "tags": [
          "user"
        ],
        "operationId": "signup",
        "responses": {
          "200": {
            "$ref": "#/responses/GenericResponse"
          },
          "default": {
            "$ref": "#/responses/GenericResponse"
          }
        }
      }
    }
  },
  "definitions": {
    "Category": {
      "description": "nolint: govet",
      "type": "object",
      "properties": {
        "CreatedAt": {
          "type": "string",
          "format": "date-time"
        },
        "DeletedAt": {
          "description": "DeletedAt is a pointer because it can be null",
          "type": "string",
          "format": "date-time"
        },
        "ID": {
          "type": "integer",
          "format": "uint64"
        },
        "Text": {
          "type": "string"
        }
      },
      "x-go-package": "country/domain/entity"
    },
    "Response": {
      "type": "object",
      "properties": {
        "Message": {
          "type": "string"
        }
      },
      "x-go-package": "country/domain/entity"
    },
    "User": {
      "description": "nolint: govet",
      "type": "object",
      "properties": {
        "CreatedAt": {
          "type": "string",
          "format": "date-time"
        },
        "DeletedAt": {
          "description": "DeletedAt is a pointer because it can be null",
          "type": "string",
          "format": "date-time"
        },
        "Email": {
          "type": "string"
        },
        "ID": {
          "type": "integer",
          "format": "uint64"
        },
        "Name": {
          "type": "string"
        },
        "Password": {
          "type": "string"
        },
        "Phone": {
          "type": "string"
        },
        "Profile": {
          "type": "string"
        },
        "Role": {
          "type": "integer",
          "format": "uint8"
        },
        "Verified": {
          "type": "boolean"
        }
      },
      "x-go-package": "country/domain/entity"
    }
  },
  "responses": {
    "GenericResponse": {
      "description": "",
      "schema": {
        "$ref": "#/definitions/Response"
      }
    },
    "GetAllCategoriesResponse": {
      "description": "",
      "schema": {
        "type": "array",
        "items": {
          "$ref": "#/definitions/Category"
        }
      }
    },
    "GetAllRegionsResponse": {
      "description": "",
      "schema": {
        "type": "array",
        "items": {
          "$ref": "#/definitions/Category"
        }
      }
    },
    "GetAllUsersResponse": {
      "description": "",
      "schema": {
        "type": "array",
        "items": {
          "$ref": "#/definitions/User"
        }
      }
    },
    "GetOneCategoriesResponse": {
      "description": "",
      "schema": {
        "$ref": "#/definitions/Category"
      }
    },
    "GetOneRegionsResponse": {
      "description": "",
      "schema": {
        "$ref": "#/definitions/Category"
      }
    },
    "GetOneUserResponse": {
      "description": "",
      "schema": {
        "$ref": "#/definitions/User"
      }
    }
  }
}